fly_book_bot_sender/__init__.py
fly_book_bot_sender-0.1.8.dist-info/LICENSE
fly_book_bot_sender-0.1.8.dist-info/METADATA
fly_book_bot_sender-0.1.8.dist-info/WHEEL
fly_book_bot_sender-0.1.8.dist-info/top_level.txt
fly_book_bot_sender-0.1.8.dist-info/RECORD
