Metadata-Version: 2.1
Name: fly-book-bot-sender
Version: 0.1.8
Summary: Send msg to fly book use bot
Home-page: https://github.com/devzwy/FlyBookBotMsgSender
Author: devzwy
Author-email: dev_zwy@aliyun.com
License: MIT
Classifier: License :: OSI Approved :: MIT License
Classifier: Programming Language :: Python
Classifier: Programming Language :: Python :: 3
Classifier: Programming Language :: Python :: 3.6
Classifier: Programming Language :: Python :: 3.7
Classifier: Programming Language :: Python :: 3.8
Classifier: Programming Language :: Python :: 3.9
Classifier: Programming Language :: Python :: Implementation :: CPython
Classifier: Programming Language :: Python :: Implementation :: PyPy
Requires-Python: >=3.6.0
License-File: LICENSE
Requires-Dist: requests
Requires-Dist: requests-toolbelt
